oz_defender/__init__.py
oz_defender/relay/__init__.py
oz_defender/relay/client.py
oz_defender/relay/exceptions.py
oz_defender-0.1.1.dist-info/WHEEL
oz_defender-0.1.1.dist-info/entry_points.txt
oz_defender-0.1.1.dist-info/METADATA
oz_defender-0.1.1.dist-info/RECORD
