Metadata-Version: 2.1
Name: oz-defender
Version: 0.1.1
Summary: 
Home-page: https://github.com/franklin-systems/oz-defender
License: MIT
Keywords: openzeppelin,open zeppelin,oz,defender,ethereum,relayer,gasless,api
Author: Franklin Developers
Author-email: developers@hellofranklin.co
Requires-Python: >=3.10,<4.0
Classifier: License :: OSI Approved :: MIT License
Classifier: Programming Language :: Python :: 3
Classifier: Programming Language :: Python :: 3.10
Classifier: Programming Language :: Python :: 3.11
Requires-Dist: pycognito (>=2022.12.0,<2023.0.0)
Requires-Dist: pytest-mock (>=3.10.0,<4.0.0)
Requires-Dist: requests (>=2.28.2,<3.0.0)
Project-URL: Repository, https://github.com/franklin-systems/oz-defender
